cdk8s_aws_alb_ingress_controller/__init__.py
cdk8s_aws_alb_ingress_controller/py.typed
cdk8s_aws_alb_ingress_controller/_jsii/__init__.py
cdk8s_aws_alb_ingress_controller/_jsii/cdk8s-aws-alb-ingress-controller@1.0.0.jsii.tgz
cdk8s_aws_alb_ingress_controller-1.0.0.dist-info/METADATA
cdk8s_aws_alb_ingress_controller-1.0.0.dist-info/WHEEL
cdk8s_aws_alb_ingress_controller-1.0.0.dist-info/top_level.txt
cdk8s_aws_alb_ingress_controller-1.0.0.dist-info/RECORD
