Metadata-Version: 2.1
Name: cdk8s-aws-alb-ingress-controller
Version: 1.0.0
Summary: cdk8s-aws-alb-ingress-controller is an CDK8S construct library that provides AWS Alb Ingress Controller Deplyment Configure.
Home-page: https://github.com/guan840912/cdk8s-aws-alb-ingress-controller.git
Author: Neil Kuan<guan840912@gmail.com>
License: Apache-2.0
Project-URL: Source, https://github.com/guan840912/cdk8s-aws-alb-ingress-controller.git
Platform: UNKNOWN
Classifier: Intended Audience :: Developers
Classifier: Operating System :: OS Independent
Classifier: Programming Language :: JavaScript
Classifier: Programming Language :: Python :: 3 :: Only
Classifier: Programming Language :: Python :: 3.6
Classifier: Programming Language :: Python :: 3.7
Classifier: Programming Language :: Python :: 3.8
Classifier: Typing :: Typed
Classifier: Development Status :: 5 - Production/Stable
Classifier: License :: OSI Approved
Requires-Python: >=3.6
Requires-Dist: aws-cdk.aws-iam (<2.0.0,>=1.74.0)
Requires-Dist: aws-cdk.core (<2.0.0,>=1.74.0)
Requires-Dist: cdk8s-plus (<0.34.0,>=0.33.0)
Requires-Dist: cdk8s (<0.34.0,>=0.33.0)
Requires-Dist: constructs (<4.0.0,>=3.2.7)
Requires-Dist: jsii (<2.0.0,>=1.14.0)
Requires-Dist: publication (>=0.0.3)
